easycit/__init__.py
easycit/__main__.py
easycit/cli.py
easycit-0.2.1.dist-info/LICENSE
easycit-0.2.1.dist-info/METADATA
easycit-0.2.1.dist-info/WHEEL
easycit-0.2.1.dist-info/entry_points.txt
easycit-0.2.1.dist-info/RECORD
