Metadata-Version: 2.1
Name: easycit
Version: 0.2.1
Summary: Easily create citations from URLs
License: Apache-2.0
Author: Scott Carvalho
Author-email: scottcarvalho71@gmail.com
Requires-Python: >=3.8,<4.0
Classifier: License :: OSI Approved :: Apache Software License
Classifier: Programming Language :: Python :: 3
Classifier: Programming Language :: Python :: 3.8
Classifier: Programming Language :: Python :: 3.9
Classifier: Programming Language :: Python :: 3.10
Classifier: Programming Language :: Python :: 3.11
Classifier: Programming Language :: Python :: 3.12
Requires-Dist: beautifulsoup4 (>=4.12.3,<5.0.0)
Requires-Dist: click (>=8.1.7,<9.0.0)
Requires-Dist: click-default-group (>=1.2.4,<2.0.0)
Requires-Dist: pyperclip (>=1.9.0,<2.0.0)
Requires-Dist: requests (>=2.32.3,<3.0.0)
Requires-Dist: sqlite-utils (>=3.36,<4.0)
